setup.py
zwc.py
zwc.egg-info/PKG-INFO
zwc.egg-info/SOURCES.txt
zwc.egg-info/dependency_links.txt
zwc.egg-info/entry_points.txt
zwc.egg-info/requires.txt
zwc.egg-info/top_level.txt