Metadata-Version: 1.0
Name: zwc
Version: 0.3.0
Summary: Chinese word count tool
Home-page: https://github.com/physacco/zwc
Author: physacco
Author-email: physacco@gmail.com
License: MIT
Platform: UNKNOWN
